fastgear/__init__.py
fastgear/applications.py
fastgear/common/__init__.py
fastgear/common/database/__init__.py
fastgear/common/database/abstract_repository.py
fastgear/common/database/redis/__init__.py
fastgear/common/database/redis/client.py
fastgear/common/database/sqlalchemy/__init__.py
fastgear/common/database/sqlalchemy/async_base_repository.py
fastgear/common/database/sqlalchemy/base.py
fastgear/common/database/sqlalchemy/base_entity.py
fastgear/common/database/sqlalchemy/session.py
fastgear/common/database/sqlalchemy/soft_delete_mixin.py
fastgear/common/database/sqlalchemy/sync_base_repository.py
fastgear/common/database/sqlalchemy/repository_utils/__init__.py
fastgear/common/database/sqlalchemy/repository_utils/base_repository_utils.py
fastgear/common/database/sqlalchemy/repository_utils/inject_db_parameter_decorator.py
fastgear/common/database/sqlalchemy/repository_utils/statement_constructor.py
fastgear/common/schema/__init__.py
fastgear/common/schema/base_schema.py
fastgear/common/schema/custom_base_model_schema.py
fastgear/common/schema/exception_response_schema.py
fastgear/constants/__init__.py
fastgear/constants/regex_expressions.py
fastgear/decorators/__init__.py
fastgear/decorators/controller_decorator.py
fastgear/decorators/db_session_decorator.py
fastgear/decorators/pagination_with_search_decorator.py
fastgear/decorators/simple_pagination_decorator.py
fastgear/handlers/__init__.py
fastgear/handlers/http_exceptions_handler.py
fastgear/middlewares/__init__.py
fastgear/middlewares/db_session_middleware.py
fastgear/types/__init__.py
fastgear/types/base_settings.py
fastgear/types/custom_base_exception.py
fastgear/types/custom_enum.py
fastgear/types/custom_pages.py
fastgear/types/delete_options.py
fastgear/types/delete_result.py
fastgear/types/find_many_options.py
fastgear/types/find_one_options.py
fastgear/types/generic_types_var.py
fastgear/types/http_exceptions.py
fastgear/types/pagination.py
fastgear/types/update_options.py
fastgear-0.5.0.dist-info/licenses/LICENSE
fastgear-0.5.0.dist-info/METADATA
fastgear-0.5.0.dist-info/WHEEL
fastgear-0.5.0.dist-info/top_level.txt
fastgear-0.5.0.dist-info/RECORD
