Metadata-Version: 2.4
Name: fastgear
Version: 0.5.0
Summary: A personal utility library I've developed to streamline and optimize backend development with FastAPI in my projects. From generic repositories and queries to enums, error handling, and more, FastGear encompasses essential tools that have proven invaluable in my development journey, whether as a novice or a seasoned professional.
Author: Henrique Marcuzzo <henrique.souza.m06@gmail.com>
License: MIT
Requires-Python: <4.0,>=3.11
License-File: LICENSE
Requires-Dist: fastapi>=0.115.13
Requires-Dist: fastapi-pagination>=0.13.2
Requires-Dist: loguru>=0.7.3
Requires-Dist: pydantic>=2.11.7
Requires-Dist: pydantic-settings>=2.10.0
Requires-Dist: sqlalchemy>=2.0.41
Requires-Dist: sqlalchemy-utils>=0.41.2
Requires-Dist: typing-inspect>=0.9.0
Requires-Dist: uuid6>=2025.0.0
Provides-Extra: redis
Requires-Dist: redis>=6.2.0; extra == "redis"
Dynamic: license-file
